cellxgene_lamin/__init__.py
cellxgene_lamin/curate.py
cellxgene_lamin/fields.py
cellxgene_lamin/dev/_cxg_rest_api.py
cellxgene_lamin/dev/_features.py
cellxgene_lamin/dev/_gene.py
cellxgene_lamin/dev/_labels.py
cellxgene_lamin/dev/_ontology.py
cellxgene_lamin/dev/_organism.py
cellxgene_lamin/dev/datasets.py
cellxgene_lamin/schemas/__init__.py
cellxgene_lamin/schemas/_schema_versions.py
cellxgene_lamin/schemas/schema_versions.yml
cellxgene_lamin-0.3.2.dist-info/LICENSE
cellxgene_lamin-0.3.2.dist-info/WHEEL
cellxgene_lamin-0.3.2.dist-info/METADATA
cellxgene_lamin-0.3.2.dist-info/RECORD
