Metadata-Version: 2.1
Name: cellxgene_lamin
Version: 0.3.2
Summary: Manage cellxgene metadata using LaminDB.
Author-email: Lamin Labs <laminlabs@gmail.com>
Requires-Python: >=3.9
Classifier: License :: OSI Approved :: Apache Software License
Classifier: Programming Language :: Python :: 3.9
Classifier: Programming Language :: Python :: 3.10
Classifier: Programming Language :: Python :: 3.11
Classifier: Programming Language :: Python :: 3.12
Requires-Dist: lamindb[bionty,aws,zarr,jupyter]
Requires-Dist: requests
Requires-Dist: pre-commit ; extra == "dev"
Requires-Dist: nox ; extra == "dev"
Requires-Dist: pytest>=6.0 ; extra == "dev"
Requires-Dist: pytest-cov ; extra == "dev"
Requires-Dist: nbproject_test ; extra == "dev"
Project-URL: Home, https://github.com/laminlabs/cellxgene-lamin
Provides-Extra: dev
